gh_copilot_wrapper/__init__.py
gh_copilot_wrapper-0.1.2.dist-info/METADATA
gh_copilot_wrapper-0.1.2.dist-info/WHEEL
gh_copilot_wrapper-0.1.2.dist-info/entry_points.txt
gh_copilot_wrapper-0.1.2.dist-info/RECORD
